encrypting/__init__.py
encrypting-0.4.dist-info/METADATA
encrypting-0.4.dist-info/WHEEL
encrypting-0.4.dist-info/top_level.txt
encrypting-0.4.dist-info/RECORD
