Metadata-Version: 2.1
Name: encrypting
Version: 0.4
Summary: Simple XOR Encryptor
Author: MichaKrutoy
